cython_collect.py
pytest_cython_collect-0.2.dist-info/LICENSE
pytest_cython_collect-0.2.dist-info/METADATA
pytest_cython_collect-0.2.dist-info/WHEEL
pytest_cython_collect-0.2.dist-info/entry_points.txt
pytest_cython_collect-0.2.dist-info/top_level.txt
pytest_cython_collect-0.2.dist-info/RECORD
