Metadata-Version: 2.1
Name: pytest-cython-collect
Version: 0.2
Summary: UNKNOWN
Home-page: https://github.com/Baekalfen/pytest-cython-collect
Author: Mads Ynddal
Author-email: mads@ynddal.dk
License: UNKNOWN
Platform: UNKNOWN
Classifier: Framework :: Pytest
License-File: LICENSE
Requires-Dist: pytest
